sprig_essentials/__init__.py
sprig_essentials/core.py
sprig_essentials/graphics/__init__.py
sprig_essentials/graphics/images.py
sprig_essentials/graphics/shapes.py
sprig_essentials/graphics/text.py
sprig_essentials/io/__init__.py
sprig_essentials/io/audio.py
sprig_essentials/io/buttons.py
sprig_essentials/io/display.py
sprig_essentials/io/led.py
sprig_essentials-0.5.0.dist-info/LICENSE
sprig_essentials-0.5.0.dist-info/METADATA
sprig_essentials-0.5.0.dist-info/WHEEL
sprig_essentials-0.5.0.dist-info/top_level.txt
sprig_essentials-0.5.0.dist-info/RECORD
