Metadata-Version: 2.1
Name: sprig_essentials
Version: 0.5.0
Summary: Simplifying the process of creating games and apps for the Sprig.
Author-email: Sooraj Sannabhadti <developer.soorajs@gmail.com>
Project-URL: Homepage, https://github.com/WhenLifeHandsYouLemons/sprig_essentials
Project-URL: Bug Tracker, https://github.com/WhenLifeHandsYouLemons/sprig_essentials/issues
Classifier: Programming Language :: Python :: 3
Classifier: License :: OSI Approved :: MIT License
Classifier: Operating System :: OS Independent
Requires-Python: >=3.8
License-File: LICENSE
